paayes/__init__.py
paayes/api_requestor.py
paayes/error.py
paayes/http_client.py
paayes/multipart_data_generator.py
paayes/oauth.py
paayes/oauth_error.py
paayes/object_classes.py
paayes/paayes_object.py
paayes/paayes_response.py
paayes/request_metrics.py
paayes/six.py
paayes/util.py
paayes/version.py
paayes/webhook.py
paayes/api_resources/__init__.py
paayes/api_resources/account.py
paayes/api_resources/account_link.py
paayes/api_resources/alipay_account.py
paayes/api_resources/apple_pay_domain.py
paayes/api_resources/application_fee.py
paayes/api_resources/application_fee_refund.py
paayes/api_resources/balance.py
paayes/api_resources/balance_transaction.py
paayes/api_resources/bank_account.py
paayes/api_resources/bitcoin_receiver.py
paayes/api_resources/bitcoin_transaction.py
paayes/api_resources/capability.py
paayes/api_resources/card.py
paayes/api_resources/charge.py
paayes/api_resources/country_spec.py
paayes/api_resources/coupon.py
paayes/api_resources/credit_note.py
paayes/api_resources/credit_note_line_item.py
paayes/api_resources/customer.py
paayes/api_resources/customer_balance_transaction.py
paayes/api_resources/dispute.py
paayes/api_resources/ephemeral_key.py
paayes/api_resources/error_object.py
paayes/api_resources/event.py
paayes/api_resources/exchange_rate.py
paayes/api_resources/file.py
paayes/api_resources/file_link.py
paayes/api_resources/invoice.py
paayes/api_resources/invoice_item.py
paayes/api_resources/invoice_line_item.py
paayes/api_resources/issuer_fraud_record.py
paayes/api_resources/line_item.py
paayes/api_resources/list_object.py
paayes/api_resources/login_link.py
paayes/api_resources/mandate.py
paayes/api_resources/order.py
paayes/api_resources/order_return.py
paayes/api_resources/payment_intent.py
paayes/api_resources/payment_method.py
paayes/api_resources/payout.py
paayes/api_resources/person.py
paayes/api_resources/plan.py
paayes/api_resources/price.py
paayes/api_resources/product.py
paayes/api_resources/promotion_code.py
paayes-2.60.0.dist-info/LICENSE
paayes-2.60.0.dist-info/METADATA
paayes-2.60.0.dist-info/WHEEL
paayes-2.60.0.dist-info/top_level.txt
paayes-2.60.0.dist-info/RECORD
