Metadata-Version: 2.1
Name: paayes
Version: 2.60.0
Summary: Python bindings for the Paayes API
Home-page: https://github.com/paayes/paayes-python
Author: Paayes
Author-email: support@paayes.com
License: MIT
Project-URL: Bug Tracker, https://github.com/paayes/paayes-python/issues
Project-URL: Documentation, https://docs.paayes.com/api/python
Project-URL: Source Code, https://github.com/paayes/paayes-python
Keywords: paayes api payments
Classifier: Development Status :: 5 - Production/Stable
Classifier: Intended Audience :: Developers
Classifier: License :: OSI Approved :: MIT License
Classifier: Operating System :: OS Independent
Classifier: Programming Language :: Python
Classifier: Programming Language :: Python :: 2
Classifier: Programming Language :: Python :: 2.7
Classifier: Programming Language :: Python :: 3
Classifier: Programming Language :: Python :: 3.4
Classifier: Programming Language :: Python :: 3.5
Classifier: Programming Language :: Python :: 3.6
Classifier: Programming Language :: Python :: 3.7
Classifier: Programming Language :: Python :: 3.8
Classifier: Programming Language :: Python :: 3.9
Classifier: Programming Language :: Python :: Implementation :: PyPy
Classifier: Topic :: Software Development :: Libraries :: Python Modules
Requires-Python: >=2.7, !=3.0.*, !=3.1.*, !=3.2.*, !=3.3.*
License-File: LICENSE
Requires-Dist: requests[security] (>=2.20) ; python_version < "3.0"
Requires-Dist: requests (>=2.20) ; python_version >= "3.0"
